butler/__init__.py
butler/client.py
butler/annotations/__init__.py
butler/annotations/annotations.py
butler/annotations/annotations_client.py
butler/annotations/bbx_utils.py
butler/annotations/document_annotation_with_image.py
butler/annotations/image_utils.py
butler/annotations/layoutlm_utils.py
butler/annotations/ner_utils.py
butler/common/__init__.py
butler/common/file_utils.py
butler/common/http_utils.py
butler/common/types.py
butler/generated/__init__.py
butler/generated/client.py
butler/generated/types.py
butler/generated/api/__init__.py
butler/generated/api/apps/__init__.py
butler/generated/api/apps/get_app_run_status.py
butler/generated/api/apps/get_document_extraction_results.py
butler/generated/api/apps/upload_documents.py
butler/generated/api/auth/__init__.py
butler/generated/api/auth/login.py
butler/generated/api/models/__init__.py
butler/generated/api/models/create_custom_model.py
butler/generated/api/models/get_document_enhanced_results.py
butler/generated/api/models/get_model.py
butler/generated/api/models/get_training_document.py
butler/generated/api/models/get_training_documents.py
butler/generated/api/models/train_custom_model.py
butler/generated/api/models/update_document_labels.py
butler/generated/api/queues/__init__.py
butler/generated/api/queues/extract_document.py
butler/generated/api/queues/get_extraction_results.py
butler/generated/api/queues/upload_documents_to_queue.py
butler/generated/models/__init__.py
butler/generated/models/app_run_status.py
butler/generated/models/app_run_status_dto.py
butler/generated/models/base_model_type.py
butler/generated/models/block_dto.py
butler/generated/models/block_result_dto.py
butler/generated/models/block_type.py
butler/generated/models/bounding_box_dto.py
butler/generated/models/column_dto.py
butler/generated/models/create_model_dto.py
butler/generated/models/doc_ex_block_type.py
butler/generated/models/doc_ex_confidence.py
butler/generated/models/document_enhanced_result_dto.py
butler_sdk-1.0.0.dist-info/LICENSE
butler_sdk-1.0.0.dist-info/METADATA
butler_sdk-1.0.0.dist-info/WHEEL
butler_sdk-1.0.0.dist-info/top_level.txt
butler_sdk-1.0.0.dist-info/RECORD
