Metadata-Version: 2.1
Name: butler-sdk
Version: 1.0.0
Summary: Butler Python SDK
Home-page: https://butlerlabs.ai
Author: Butler Labs
Author-email: support@butlerlabs.ai
Project-URL: Documentation, https://docs.butlerlabs.ai/reference/welcome
Keywords: Butler,AutoML,OCR
Requires-Python: >=3.7
License-File: LICENSE
Requires-Dist: attrs (>=21.3.0)
Requires-Dist: httpx (<0.24.0,>=0.15.4)
Requires-Dist: pdf2image
Requires-Dist: pillow
Requires-Dist: python-dateutil (~=2.8.1)
Requires-Dist: typing-extensions
